vaex/ml/__init__.py
vaex/ml/_version.py
vaex/ml/catboost.py
vaex/ml/cluster.py
vaex/ml/generate.py
vaex/ml/lightgbm.py
vaex/ml/linear_model.py
vaex/ml/metrics.py
vaex/ml/pipeline.py
vaex/ml/sklearn.py
vaex/ml/spec.json
vaex/ml/spec.py
vaex/ml/state.py
vaex/ml/tensorflow.py
vaex/ml/transformations.py
vaex/ml/ui.py
vaex/ml/xgboost.py
vaex/ml/incubator/__init__.py
vaex/ml/incubator/annoy.py
vaex/ml/incubator/pygbm.py
vaex/ml/incubator/river.py
vaex_ml-0.18.3.dist-info/LICENSE.txt
vaex_ml-0.18.3.dist-info/METADATA
vaex_ml-0.18.3.dist-info/WHEEL
vaex_ml-0.18.3.dist-info/entry_points.txt
vaex_ml-0.18.3.dist-info/top_level.txt
vaex_ml-0.18.3.dist-info/RECORD
